{
  "project_info": {
    "project_number": "51433450641",
    "project_id": "testedoflutter",
    "storage_bucket": "testedoflutter.appspot.com"
  },
  "client": [
    {
      "client_info": {
        "mobilesdk_app_id": "1:51433450641:android:10fae87691295e217aa330",
        "android_client_info": {
          "package_name": "com.example.firebase_test"
        }
      },
      "oauth_client": [
        {
          "client_id": "51433450641-ip63j8vr4ubr5kf1tft0nsfv4ibq5vsq.apps.googleusercontent.com",
          "client_type": 3
        }
      ],
      "api_key": [
        {
          "current_key": "AIzaSyD7jlSqmhnisTlalmja2j0l8V7k3xufSOw"
        }
      ],
      "services": {
        "appinvite_service": {
          "other_platform_oauth_client": [
            {
              "client_id": "51433450641-ip63j8vr4ubr5kf1tft0nsfv4ibq5vsq.apps.googleusercontent.com",
              "client_type": 3
            }
          ]
        }
      }
    }
  ],
  "configuration_version": "1"
}